{
    "_sku": "_8397309",
    "_upc": "_077924023309",
    "_name": "Weber Plastic Igniter Kit 3.2 in. L X 3.1 in. W For Weber",
    "_price": "$54.99",
    "Brand Name": " Weber",
    "Product Type": " Igniter Kit",
    "Dishwasher Safe": " No",
    "Grill Type": " Gas",
    "Height": " 2.3 inch",
    "Length": " 3.2 inch",
    "Number in Package": " 1 pack",
    "Packaging Type": " Boxed",
    "Width": " 3.1 inch",
    "Color/Finish": " Black",
    "Grill Compatibility": " Weber",
    "Primary Material": " Plastic",
    "Product_URL": "https://www.acehardware.com/departments/outdoor-living/grills-and-smokers/grill-replacement-parts/8397309"
}