{
    "_sku": "_2006227",
    "_upc": "_754005001776",
    "_name": "Metabo HPT 7/16 in. W X 1-1/2 in. L 16 Ga. Standard Staples 10000 pk",
    "_price": "$79.99",
    "Brand Name": " Metabo HPT",
    "Product Type": " Standard Staples",
    "Color": " Green",
    "Crown Width": " 7/16 inch",
    "Gauge": " 16 Gauge",
    "Length": " 1 1/2 inch",
    "Material": " Galvanized Steel",
    "Number in Package": " 10000 pack",
    "Packaging Type": " Boxed",
    "Coating": " Zinc",
    "Product_URL": "https://www.acehardware.com/departments/tools/fastening-tools/staples/2006227"
}