{
    "_sku": "_6392302",
    "_upc": "_047323003844",
    "_name": "iLive Wireless Bluetooth Under Cabinet Music System",
    "_price": "$69.99",
    "Brand Name": " iLive",
    "Product Type": " Under Cabinet Music System",
    "Bluetooth": " Yes",
    "Clock Included": " Yes",
    "Color": " Silver",
    "Height": " 2.8 inch",
    "Length": " 11.42 inch",
    "Power Source": " AC/DC Adapter",
    "Video Capability": " No",
    "Warranty": " 90 Day Limited",
    "Width": " 11.54 inch",
    "Wireless": " Yes",
    "Smart-Enabled": " Yes",
    "What's Included": "Mounting Hardware, AC/DC Power Adapter",
    "Product_URL": "https://www.acehardware.com/departments/lighting-and-electrical/home-electronics/radios-and-speakers/6392302"
}