{
    "_sku": "_7016461",
    "_upc": "_021496370286",
    "_name": "Pennington Bermuda Grass Full Sun Grass Seed 15 lb",
    "_price": "$99.99",
    "Brand Name": " Pennington",
    "Product Type": " Grass Seed",
    "Application Season": " Multi Season",
    "Container Size": " 15 pound",
    "Coverage Area": " 15000 square foot",
    "Drought Tolerant": " Yes",
    "Grass Type": " Bermuda Grass",
    "Packaging Type": " Bagged",
    "Seed Type": " Perennial",
    "Exposure": " Full Sun",
    "Heat Tolerant": " Yes",
    "Lawn Project": " New Lawn",
    "Region": " South",
    "Size of Lawn": " Large (10000 sq ft+)",
    "Product_URL": "https://www.acehardware.com/departments/lawn-and-garden/lawn-care/grass-seeds/7016461"
}