{
    "_sku": "_3563111",
    "_upc": "_092644690143",
    "_name": "Klein Tools LCD Clamp Meter",
    "_price": "$109.99",
    "Brand Name": " Klein Tools",
    "Product Type": " Clamp Meter",
    "Batteries Included": " Yes",
    "Battery Size": " AAA",
    "Color": " Black/Orange",
    "Depth": " 9.09 inch",
    "Display Type": " LCD",
    "Height": " 9 inch",
    "Warranty": " 2 Year",
    "Width": " 3.81 inch",
    "What's Included": "Clamp Meter; Carrying Case; 41\" (1041.4 mm) Test Leads; Batteries",
    "Product_URL": "https://www.acehardware.com/departments/lighting-and-electrical/electrical-tools/meters-and-testers/3563111"
}