{
    "_sku": "_2833010",
    "_upc": "_045242003631",
    "_name": "Milwaukee Big Hawg 3-5/8 in. Carbide Tipped Hole Saw 1 pc",
    "_price": "$59.99",
    "Brand Name": " Milwaukee",
    "Sub Brand": " BIG HAWG",
    "Product Type": " Hole Saw",
    "Arbor Included": " No",
    "Cutting Depth": " 2.34 inch",
    "Diameter": " 3-5/8 inch",
    "Length": " 2.44 inch",
    "Material": " Carbide Tipped",
    "Number in Package": " 1 piece",
    "Usage": " Abrasive Materials and Nail-embedded Wood",
    "Compatible Arbors": " Arbors with 5/8 in.-18 Thread",
    "Quick-Change System": " Yes",
    "Product_URL": "https://www.acehardware.com/departments/tools/power-tool-accessories/hole-saws/2833010"
}