{
    "_sku": "_7820087",
    "_upc": "_850031426139",
    "_name": "Branch Creek Entry Blended Pet Friendly Liquid Ice Melt 2.5 gal",
    "_price": "$109.99",
    "Brand Name": " Branch Creek",
    "Sub Brand": " Entry",
    "Product Type": " Ice Melt",
    "Chemical Composition": " Blended",
    "Container Size": " 2.5 gallon (US)",
    "Lowest Effective Temperature": "  -63 degree Fahrenheit",
    "Packaging Type": " Jug",
    "Pet Friendly": " Yes",
    "Product Form": " Liquid",
    "Enviromentally Friendly": " Yes",
    "Safe for Vegetation": " Yes",
    "Product_URL": "https://www.acehardware.com/ice-melt/7820087"
}