{
    "_sku": "_7029127",
    "_upc": "_044365029184",
    "_name": "Suncast 1.25 in. H X 49.65 in. W X 10 in. D Resin Shelf Kit",
    "_price": "$129.99",
    "Brand Name": " Suncast",
    "Product Type": " Shelf Kit",
    "Color": " BLACK",
    "Depth": " 10 inch",
    "Hardware included": " YEs",
    "Height": " 1.25 inch",
    "Material": " Resin",
    "Number of Shelves": " 2",
    "Packaging Type": " Boxed",
    "Weight Capacity": " 50 pound",
    "Width": " 49.65 inch",
    "What's Included": "Two Resin Shelves and Wall Mounts",
    "Product_URL": "https://www.acehardware.com/departments/storage-and-organization/shelving-and-shelving-units/shelving-units/7029127"
}