{
    "_sku": "_7005457",
    "_upc": "_817198024042",
    "_name": "Champion Load Management Module",
    "_price": "$159.99",
    "Brand Name": " Champion",
    "Product Type": " Load Management Module",
    "Height": " 8.2 inch",
    "Length": " 5.2 inch",
    "Number in Package": " 1 pack",
    "Width": " 3.8 inch",
    "Power Equipment Family": " Generators",
    "Product_URL": "https://www.acehardware.com/departments/lawn-and-garden/outdoor-power-equipment/outdoor-power-accessories/7005457"
}