{
    "_sku": "_4573051",
    "_upc": "_034449809863",
    "_name": "Delta Porter Oil Rubbed Bronze Bathroom Faucet 4 in.",
    "_price": "$149.99",
    "Brand Name": " Delta",
    "Sub Brand": " Porter",
    "Product Type": " Bathroom Faucet",
    "ADA Compliant": " Yes",
    "Average Lead Content": " Low Lead",
    "Ceramic Disk Valves": " Yes",
    "Connection Size": " 1/2 inch",
    "Finish": " Oil Rubbed Bronze",
    "Flow Rate": " 1.2 Gallons per Minute",
    "Handle Type": " Lever",
    "Number of Handles": " 1",
    "Number of Installation Holes Required": " 3",
    "On Center Measurement": " 4 inch",
    "Spout Height": " 3.88 inch",
    "Spout Reach": " 4-7/8 inch",
    "Spout Type": " High Arc",
    "Style or Series": " Contemporary",
    "Product_URL": "https://www.acehardware.com/departments/plumbing/faucet-and-faucet-repair/bathroom-sink-faucets/4573051"
}