{
    "_sku": "_4324091",
    "_upc": "_034449617130",
    "_name": "Delta Leland Stainless Steel Centerset Bathroom Sink Faucet 4 in.",
    "_price": "$189.99",
    "Brand Name": " Delta",
    "Sub Brand": " Leland",
    "Product Type": " Centerset Bathroom Sink Faucet",
    "ADA Compliant": " Yes",
    "Average Lead Content": " Low Lead",
    "Connection Size": " 1/2 inch",
    "Finish": " Stainless Steel",
    "Flow Rate": " 1.2 Gallons per Minute",
    "Handle Type": " Lever",
    "Number of Handles": " 2",
    "Number of Installation Holes Required": " 3",
    "On Center Measurement": " 4 inch",
    "Spout Height": " 3.875 inch",
    "Spout Reach": " 5-1/16 inch",
    "Spout Type": " Teapot",
    "Style or Series": " Farmhouse",
    "Product_URL": "https://www.acehardware.com/departments/plumbing/faucet-and-faucet-repair/bathroom-sink-faucets/4324091"
}