{
    "_sku": "_2002176",
    "_upc": "_045242524228",
    "_name": "Milwaukee PACKOUT 16 in. Portable Modular Tool Case with Foam Insert Black/Red",
    "_price": "$79.99",
    "Brand Name": " Milwaukee",
    "Sub Brand": " PACKOUT",
    "Product Type": " Tool Case with Foam Insert",
    "Color": " Black/Red",
    "Height": " 6 inch",
    "Length": " 16 inch",
    "Lockable": " Yes",
    "Material": " Plastic",
    "Number of Compartments": " 1",
    "Style": " Portable Modular",
    "Tray Included": " No",
    "Water Resistant": " Yes",
    "Weight Capacity": " 75 pound capacity",
    "Wheeled": " No",
    "Width": " 15 inch",
    "Comfort Grip Handle": " No",
    "What's Included": "(1) PACKOUT Tool Case and (1) Foam Insert",
    "Product_URL": "https://www.acehardware.com/departments/tools/tools-storage-and-organization/tool-boxes/2002176"
}