{
    "_sku": "_6033935",
    "_upc": "_850017897434",
    "_name": "Flex Seal Family of Products Flex Seal MAX Black Liquid Rubber Sealant Coating 2.5 gal",
    "_price": "$239.99",
    "Brand Name": " Flex Seal Family of Products",
    "Sub Brand": " Flex Seal MAX",
    "Product Type": " Liquid Rubber Sealant Coating",
    "Color": " BLACK",
    "Color Family": " Black",
    "Container Size": " 2.5 gallon (US)",
    "Coverage Area": " 375 square foot",
    "Inverted Spray Ability": " No",
    "Packaging Type": " Can",
    "Primer Required": " No",
    "Time Before Recoating": " 48 hour",
    "UV Resistant": " Yes",
    "Clean Up": " Mineral Spirits",
    "Indoor or Outdoor": " Indoor and Outdoor",
    "Full Cure Time": " 48 hour",
    "Recommended Surface": " Most Surfaces",
    "What's Included": "Two 1/2 Gallons (320 oz.) Can of FLEX SEAL Liquid MAX Black",
    "Product_URL": "https://www.acehardware.com/departments/paint-and-supplies/specialty-paints/rubberized-coatings/6033935"
}