{
    "_sku": "_3207347",
    "_upc": "_026715163014",
    "_name": "Broan-NuTone 70 CFM 1.5 Sones Bathroom Ventilation Fan and Light Combination",
    "_price": "$159.99",
    "Brand Name": " Broan-NuTone",
    "Product Type": " Bathroom Ventilation Fan and Light Combination",
    "Ceiling or Wall Installation": " Ceiling",
    "Color": " White",
    "Compatible Duct Size": " 4 inch",
    "Depth": " 8-1/4 inch",
    "ETL Listed": " No",
    "Energy Star Certified": " No",
    "Fan Sound Level": " 1.5 sone",
    "Grille Material": " Polymeric",
    "HVI Certified": " Yes",
    "Height": " 6-7/8 inch",
    "Housing Material": " Metal",
    "Light": " Yes",
    "Maximum Air Volume": " 70 cubic foot per minute",
    "Nightlight": " No",
    "Packaging Type": " Boxed",
    "UL Listed": " Yes",
    "Warranty": " 1 Year",
    "Watts": " 125 watt",
    "Width": " 6-7/8 inch",
    "Product_URL": "https://www.acehardware.com/departments/heating-and-cooling/portable-and-exhaust-fans/bathroom-fans/3207347"
}