{
    "_sku": "_4410569",
    "_upc": "_089301421004",
    "_name": "Mr. Heater 15000 Btu/h 300 sq ft Infrared Propane Tank Top Heater",
    "_price": "$59.99",
    "Brand Name": " Mr. Heater",
    "Product Type": " Tank Top Heater",
    "Automatic Delay Shutoff": " Yes",
    "Built In Timer": " No",
    "CSA LIsted": " Yes",
    "Color": " White",
    "Depth": " 9 inch",
    "ETL Listed": " No",
    "Heat Output": " 15000 British thermal unit per hour",
    "Heater Type": " Infrared",
    "Heating Area": " 300 square foot",
    "Height": " 11 inch",
    "Material": " Steel",
    "Power or Fuel Type": " Propane",
    "Thermostat": " No",
    "UL Listed": " No",
    "Wheeled": " No",
    "Width": " 8 inch",
    "Indoor or Outdoor": " Outdoor",
    "Heating Area Range": " 300-600 sq. ft.",
    "Product_URL": "https://www.acehardware.com/departments/heating-and-cooling/heaters/space-heaters/4410569"
}