{
    "_sku": "_7262751",
    "_upc": "_836128000017",
    "_name": "Dakota Sno Blade 36 in. W X 48 in. L Poly Wheeled Snow Shovel",
    "_price": "$129.99",
    "Brand Name": " Dakota Sno Blade",
    "Product Type": " Wheeled Snow Shovel",
    "Blade Color": " Red",
    "Blade Length": " 11 inch",
    "Blade Width": " 36 inch",
    "Blade material": " Poly",
    "Coated Blades": " Yes",
    "Handle Material": " Steel",
    "Overall Length": " 48 inch",
    "Product_URL": "https://www.acehardware.com/departments/lawn-and-garden/snow-removal-and-equipment/snow-shovels-and-pushers/7262751"
}