{
    "_sku": "_8365579",
    "_upc": "_076501201284",
    "_name": "Coleman Propane Camping Stove",
    "_price": "$124.99",
    "Brand Name": " Coleman",
    "Product Type": " Camping Stove",
    "Btus": " 20000 British thermal unit",
    "Color": " Green",
    "Compatible Fuel Container Size": " 16.4 ounce",
    "Fuel Type": " Propane",
    "Height": " 4 inch",
    "Length": " 22 inch",
    "Material": " Aluminized Steel",
    "Number of Burners": " 2 burners",
    "Tank Included": " No",
    "Width": " 13 inch",
    "Product_URL": "https://www.acehardware.com/departments/outdoor-living/sporting-goods/camping-stoves/8365579"
}