{
    "_sku": "_4892014",
    "_upc": "_026508276198",
    "_name": "Moen Hilliard Brushed Nickel Bathroom Faucet 4 in.",
    "_price": "$89.99",
    "Brand Name": " Moen",
    "Sub Brand": " HIlliard",
    "Product Type": " Bathroom Faucet",
    "ADA Compliant": " Yes",
    "Connection Size": " 1/2 inch",
    "Finish": " Brushed Nickel",
    "Fits For": " IPS",
    "Flow Rate": " 1.2 Gallons per Minute",
    "Handle Type": " Lever",
    "Motion Sensing": " No",
    "Number of Handles": " 2",
    "Number of Installation Holes Required": " 3",
    "On Center Measurement": " 4 inch",
    "Spout Height": " 6.93 inch",
    "Spout Reach": " 4.70 inch",
    "Spout Type": " High Arc",
    "Style or Series": " Traditional",
    "What's Included": "Faucet and Non-Metal Pushdown Waste Assembly",
    "Product_URL": "https://www.acehardware.com/departments/plumbing/faucet-and-faucet-repair/bathroom-sink-faucets/4892014"
}