{
    "_sku": "_3002908",
    "_upc": "_026715260904",
    "_name": "Broan-NuTone Flex Series 80 CFM 0.7 Sones Bathroom Exhaust Fan",
    "_price": "$119.99",
    "Brand Name": " Broan-NuTone",
    "Sub Brand": " Flex Series",
    "Product Type": " Bathroom Exhaust Fan",
    "Ceiling or Wall Installation": " Ceiling",
    "Color": " White",
    "Compatible Duct Size": " 4 inch",
    "Depth": " 12.25 inch",
    "ETL Listed": " No",
    "Energy Star Certified": " Yes",
    "Fan Sound Level": " 0.7 sone",
    "Grille Material": " Polymeric",
    "HVI Certified": " Yes",
    "Height": " 5.75 inch",
    "Housing Material": " Steel",
    "Light": " No",
    "Maximum Air Volume": " 80 cubic foot per minute",
    "Nightlight": " No",
    "Packaging Type": " Boxed",
    "UL Listed": " Yes",
    "Warranty": " 3 Year",
    "Watts": " 24.5 watt",
    "Width": " 12.25 inch",
    "Product_URL": "https://www.acehardware.com/departments/heating-and-cooling/portable-and-exhaust-fans/bathroom-fans/3002908"
}