{
    "_sku": "_4021217",
    "_upc": "_050375027508",
    "_name": "InSinkErator Power 1 HP Continuous Feed Garbage Disposal",
    "_price": "$219.99",
    "Brand Name": " InSinkErator",
    "Sub Brand": " Power",
    "Product Type": " Garbage Disposal",
    "Blade material": " Stainless Steel",
    "Color": " Black/Silver",
    "Diameter": " 8.25 inch",
    "Dishwasher Drain Connection": " Yes",
    "Grinding Speed": " 1725 revolutions per minute",
    "Height": " 12 inch",
    "Horsepower": " 1 HP (horsepower)",
    "Housing Material": " Galvanized Steel",
    "Noise Insulation": " Yes",
    "Warranty": " 7 year",
    "Disposal Feed": " Continuous Feed",
    "What's Included": "Hardware Adapter",
    "Product_URL": "https://www.acehardware.com/departments/plumbing/garbage-disposals-and-parts/garbage-disposals/4021217"
}