{
    "_sku": "_4086476",
    "_upc": "_671090004478",
    "_name": "Woodford Iowa 3/4 in. FIP MPT Steel Yard Hydrant",
    "_price": "$199.99",
    "Brand Name": " Woodford",
    "Sub Brand": " Iowa",
    "Product Type": " Yard Hydrant",
    "End 1 Size": " 3/4 inch",
    "End 1 Type": " FIP",
    "End 2 Type": " MPT",
    "Finish": " Galvanized",
    "Frost-Proof": " Yes",
    "Handle Type": " Lever",
    "Length": " 48 inch",
    "Material": " Steel",
    "Maximum Pressure": " 125 pound per square inch",
    "Maximum Temperature": " 120 degree Fahrenheit",
    "Number in Package": " 1",
    "Packaging Type": " Boxed",
    "Lead Content": " Less than 0.25%",
    "Anti-Siphon": " No",
    "What's Included": "Y34 Yard Hydrant",
    "Product_URL": "https://www.acehardware.com/departments/plumbing/valves/rough-faucets-and-hose-bibbs/4086476"
}