{
    "_sku": "_5363825",
    "_upc": "_026634165823",
    "_name": "Amerock Inspirations Round Cabinet Knob 1-1/4 in. D 1 in. Oil Rubbed Bronze 10 pk",
    "_price": "$59.99",
    "Brand Name": " Amerock",
    "Product Type": " Cabinet Knob",
    "Diameter": " 1 1/4 inch",
    "Finish": " Oil Rubbed Bronze",
    "Hardware included": " YEs",
    "Material": " Zinc",
    "Number in Package": " 10 pack",
    "Packaging Type": " Blister Pack",
    "Projection": " 1 inch",
    "Screw Size": " 8-32 x 1 inch",
    "Shape": " Round",
    "Style": " Inspirations",
    "What's Included": "Includes mounting hardware: (Size(s):#8-32 x 1in Truss Head Machine Screw)",
    "Product_URL": "https://www.acehardware.com/departments/hardware/cabinet-and-furniture-hardware/cabinet-knobs/5363825"
}