{
    "_sku": "_6396212",
    "_upc": "_090271001202",
    "_name": "Honeywell QuietClean HEPA Air Purifier 170 sq ft",
    "_price": "$199.99",
    "Brand Name": " Honeywell",
    "Sub Brand": " QuietClean",
    "Product Type": " Air Purifier",
    "AHAM Certified": " Yes",
    "CSA LIsted": " No",
    "Color": " BLACK",
    "Control Type": " Electrical",
    "Coverage Area": " 170 square foot",
    "Depth": " 10-1/8 inch",
    "Effectiveness": " 99 percent",
    "Energy Star Certified": " Yes",
    "Filter Type": " HEPA",
    "Height": " 29 inch",
    "Portable": " Yes",
    "UL Listed": " Yes",
    "Volts": " 120 volt",
    "Wall Mountable": " No",
    "Warranty": " 5 Year",
    "Width": " 9-11/16 inch",
    "Product_URL": "https://www.acehardware.com/departments/heating-and-cooling/air-quality/air-purifiers/6396212"
}