{
    "_sku": "_71207",
    "_upc": "_651082348506",
    "_name": "Garden Craft 48 in. H X 50 ft. L Steel Welded Wire Fence 2x3 in.",
    "_price": "$69.99",
    "Brand Name": " Garden Craft",
    "Product Type": " Welded Wire Fence",
    "Color": " Silver",
    "Height": " 48 inch",
    "Length": " 50 foot",
    "Material": " Steel",
    "Mesh Size": " 2x3 inch",
    "Vinyl Coated": " Yes",
    "Wire Gauge": " 16 Gauge",
    "Product_URL": "https://www.acehardware.com/departments/building-supplies/gates-and-fences/agricultural-and-garden-fencing/71207"
}