{
    "_sku": "_2828028",
    "_upc": "_045242005178",
    "_name": "Milwaukee M18 FUEL 7-1/4 in. Cordless Brushless Circular Saw Kit (Battery & Charger)",
    "_price": "$449.99",
    "Brand Name": " Milwaukee",
    "Product Type": " Circular Saw",
    "Arbor Size": " 5/8 inch",
    "Bevel Capacity": " 50 degree",
    "Blade Location": " Right",
    "Corded or Cordless": " Cordless",
    "Depth Adjustment": " Yes",
    "Diameter": " 7-1/4 inch",
    "Electric Brake": " Yes",
    "Laser Guide": " No",
    "Maximum Cutting Depth at 45 Degrees": " 1-7/8 inch",
    "Maximum Cutting Depth at 90 Degrees": " 2 1/2 inch",
    "Maximum Speed": " 5800 revolutions per minute",
    "Number of Batteries Included": " 1",
    "Spindle Lock": " Yes",
    "Volts": " M18 FUEL",
    "Warranty": " 5 Year",
    "Tool Weight": " 9.05 pound",
    "Blade Change": " Keyed",
    "Battery Amp Hours": " 12 Ah",
    "Brushed or Brushless": " Brushless",
    "Kit or Tool Only": " Kit (Battery & Charger)",
    "Certifications": " UL Listed",
    "What's Included": "(1) HD12.0 Battery Pack, (1) M18 & M12 Rapid Charger, (1) Blade, (1) Blade Wrench and (1) Contractor Bag",
    "Product_URL": "https://www.acehardware.com/departments/tools/power-tools/circular-saws/2828028"
}