{
    "_sku": "_8210841",
    "_upc": "_077924074479",
    "_name": "Weber Porcelain Coated Steel Flavorizer Bar 21.5 in. L X 1.7 in. W For Weber SPIRIT 200 & 500",
    "_price": "$69.99",
    "Brand Name": " Weber",
    "Product Type": " Flavorizer Bar",
    "Dishwasher Safe": " No",
    "Grill Type": " Gas",
    "Height": " 1.7 inch",
    "Length": " 21.5 inch",
    "Number in Package": " 5 pack",
    "Packaging Type": " Boxed",
    "Width": " 1.7 inch",
    "Color/Finish": " Black",
    "Grill Compatibility": " Weber",
    "Primary Material": " Porcelain Coated Steel",
    "Grill Compatibility Series": " SPIRIT 200 & 500",
    "Product_URL": "https://www.acehardware.com/departments/outdoor-living/grills-and-smokers/grill-replacement-parts/8210841"
}