{
    "_sku": "_8079973",
    "_upc": "_841057182185",
    "_name": "Living Accents Steel Hardtop Grill Gazebo 8 ft. H X 8 ft. W X 5 ft. L",
    "_price": "$549.99",
    "Brand Name": " Living Accents",
    "Product Type": " Grill Gazebo",
    "Assembly Required": " Yes",
    "Canopy Material": " Steel",
    "Frame Color": " Black",
    "Frame Material": " Steel",
    "Height": " 8 foot",
    "Length": " 5 foot",
    "Number of Sides": " 4",
    "Rain Proof": " Yes",
    "Style": " Hardtop",
    "Width": " 8 foot",
    "Product Category": " Gazebo",
    "Number of Legs": " 4",
    "What's Included": "Metal Frame",
    "Product_URL": "https://www.acehardware.com/departments/outdoor-living/patio-furniture/canopies-and-gazebos/8079973"
}